{
  "project_info": {
    "project_number": "135187193199",
    "project_id": "typing-80edd",
    "storage_bucket": "typing-80edd.firebasestorage.app"
  },
  "client": [
    {
      "client_info": {
        "mobilesdk_app_id": "1:135187193199:android:815f3958b212811daa1c9a",
        "android_client_info": {
          "package_name": "com.example.my_final_app"
        }
      },
      "oauth_client": [],
      "api_key": [
        {
          "current_key": "AIzaSyAEMPuSFX-dGSMQ-Fq9EbMQwHj8bVAYyTM"
        }
      ],
      "services": {
        "appinvite_service": {
          "other_platform_oauth_client": []
        }
      }
    },
    {
      "client_info": {
        "mobilesdk_app_id": "1:135187193199:android:9b761983e9039cebaa1c9a",
        "android_client_info": {
          "package_name": "com.example.my_flutter_app"
        }
      },
      "oauth_client": [],
      "api_key": [
        {
          "current_key": "AIzaSyAEMPuSFX-dGSMQ-Fq9EbMQwHj8bVAYyTM"
        }
      ],
      "services": {
        "appinvite_service": {
          "other_platform_oauth_client": []
        }
      }
    },
    {
      "client_info": {
        "mobilesdk_app_id": "1:135187193199:android:7eee9011699e082eaa1c9a",
        "android_client_info": {
          "package_name": "com.example.typing_chat_fixed"
        }
      },
      "oauth_client": [],
      "api_key": [
        {
          "current_key": "AIzaSyAEMPuSFX-dGSMQ-Fq9EbMQwHj8bVAYyTM"
        }
      ],
      "services": {
        "appinvite_service": {
          "other_platform_oauth_client": []
        }
      }
    }
  ],
  "configuration_version": "1"
}